giaola_role_permissions/__init__.py
giaola_role_permissions/admin.py
giaola_role_permissions/apps.py
giaola_role_permissions/decorators.py
giaola_role_permissions/exceptions.py
giaola_role_permissions/loader.py
giaola_role_permissions/mixins.py
giaola_role_permissions/models.py
giaola_role_permissions/permissions.py
giaola_role_permissions/roles.py
giaola_role_permissions/shortcuts.py
giaola_role_permissions/utils.py
giaola_role_permissions/verifications.py
giaola_role_permissions/templatetags/__init__.py
giaola_role_permissions/templatetags/permission_tags.py
giaola_role_permissions/tests/__init__.py
giaola_role_permissions/tests/mock_urls.py
giaola_role_permissions/tests/test_decorators.py
giaola_role_permissions/tests/test_mixins.py
giaola_role_permissions/tests/test_permissions.py
giaola_role_permissions/tests/test_roles.py
giaola_role_permissions/tests/test_shortcuts.py
giaola_role_permissions/tests/test_template_tags.py
giaola_role_permissions/tests/test_verifications.py
giaola_role_permissions-1.2.0.dist-info/DESCRIPTION.rst
giaola_role_permissions-1.2.0.dist-info/METADATA
giaola_role_permissions-1.2.0.dist-info/RECORD
giaola_role_permissions-1.2.0.dist-info/WHEEL
giaola_role_permissions-1.2.0.dist-info/metadata.json
giaola_role_permissions-1.2.0.dist-info/top_level.txt
