Metadata-Version: 2.0
Name: giaola-role-permissions
Version: 1.2.0
Summary: A django app for role based permissions.
Home-page: https://github.com/Giaola/django-role-permissions
Author: Marsel Tzatzo
Author-email: tmarselg@gmail.com
License: MIT
Platform: UNKNOWN
Classifier: Development Status :: 5 - Production/Stable
Classifier: Intended Audience :: Developers
Classifier: License :: OSI Approved :: MIT License
Classifier: Natural Language :: English
Classifier: Programming Language :: Python :: 2
Classifier: Programming Language :: Python :: 2.7
Classifier: Programming Language :: Python :: 3
Classifier: Programming Language :: Python :: 3.2
Classifier: Programming Language :: Python :: 3.3
Classifier: Programming Language :: Python :: 3.4
Classifier: Programming Language :: Python :: 3.5
Classifier: Programming Language :: Python :: 3.6
Requires-Dist: Django (<=1.11,>=1.5)
Requires-Dist: django-discover-runner
Requires-Dist: six
